spectrum_io/__init__.py
spectrum_io/__main__.py
spectrum_io/d/__init__.py
spectrum_io/d/bruker.py
spectrum_io/d/masterPeak.py
spectrum_io/d/masterSpectrum.py
spectrum_io/d/peak.py
spectrum_io/file/__init__.py
spectrum_io/file/csv.py
spectrum_io/file/hdf5.py
spectrum_io/file/parquet.py
spectrum_io/py.typed
spectrum_io/raw/__init__.py
spectrum_io/raw/msraw.py
spectrum_io/raw/thermo_raw.py
spectrum_io/search_result/__init__.py
spectrum_io/search_result/mascot.py
spectrum_io/search_result/maxquant.py
spectrum_io/search_result/msamanda.py
spectrum_io/search_result/msfragger.py
spectrum_io/search_result/openms.py
spectrum_io/search_result/sage.py
spectrum_io/search_result/scout.py
spectrum_io/search_result/search_results.py
spectrum_io/search_result/xisearch.py
spectrum_io/spectral_library/__init__.py
spectrum_io/spectral_library/digest.py
spectrum_io/spectral_library/dlib/myPrositLib.dlib
spectrum_io/spectral_library/dlib.py
spectrum_io/spectral_library/msp/myPrositLib.msp
spectrum_io/spectral_library/msp.py
spectrum_io/spectral_library/spectral_library.py
spectrum_io/spectral_library/spectronaut/myPrositLib.csv
spectrum_io/spectral_library/spectronaut.py
spectrum_io-0.8.0.dist-info/LICENSE
spectrum_io-0.8.0.dist-info/METADATA
spectrum_io-0.8.0.dist-info/WHEEL
spectrum_io-0.8.0.dist-info/entry_points.txt
spectrum_io-0.8.0.dist-info/RECORD
