Metadata-Version: 2.3
Name: spectrum_io
Version: 0.8.0
Summary: IO related functionalities for oktoberfest.
License: MIT
Author: Wilhelmlab at Technical University of Munich
Requires-Python: >=3.10,<3.14.0
Classifier: License :: OSI Approved :: MIT License
Classifier: Programming Language :: Python :: 3
Classifier: Programming Language :: Python :: 3.10
Classifier: Programming Language :: Python :: 3.11
Classifier: Programming Language :: Python :: 3.12
Classifier: Programming Language :: Python :: 3.13
Requires-Dist: PyYAML (>=5.4.1)
Requires-Dist: alphatims (>=1.0.8,<2.0.0)
Requires-Dist: click (>=8.0.0)
Requires-Dist: h5py (>=3.1.0,<4.0.0)
Requires-Dist: lxml (>=4.5.2,<6.0.0)
Requires-Dist: numpy (>=2.0)
Requires-Dist: pandas (>=1.3,<3.0)
Requires-Dist: pyarrow (>=16.0.0)
Requires-Dist: pymzml (>=2.5.0,<3.0.0)
Requires-Dist: pyopenms (>=3.0.0)
Requires-Dist: pyteomics (>=4.3.3,<5.0.0)
Requires-Dist: rich (>=10.3.0)
Requires-Dist: sortedcontainers (>=2.4.0,<3.0.0)
Requires-Dist: spectrum-fundamentals (>=0.9.0,<0.10.0)
Project-URL: Documentation, https://spectrum-io.readthedocs.io
Project-URL: Homepage, https://github.com/wilhelm-lab/spectrum_io
Project-URL: Repository, https://github.com/wilhelm-lab/spectrum_io
